Orange3MNE/__init__.py
Orange3MNE/EegClassification/__init__.py
Orange3MNE/EegClassification/models/CNNClassifier.py
Orange3MNE/EegClassification/models/SkLearnClassifier.py
Orange3MNE/EegClassification/models/__init__.py
Orange3MNE/EegClassification/structs/ClassificationStruct.py
Orange3MNE/EegClassification/structs/TestTrainStruct.py
Orange3MNE/EegClassification/structs/__init__.py
Orange3MNE/EegClassification/widgets/AbstractClassifierRunner.py
Orange3MNE/EegClassification/widgets/CNN.py
Orange3MNE/EegClassification/widgets/CNNReshape.py
Orange3MNE/EegClassification/widgets/ConcatenateClassificationStructs.py
Orange3MNE/EegClassification/widgets/CreateClassificationStruct.py
Orange3MNE/EegClassification/widgets/LDA.py
Orange3MNE/EegClassification/widgets/MatToVectors.py
Orange3MNE/EegClassification/widgets/NeighborAverage.py
Orange3MNE/EegClassification/widgets/PrepareVectors.py
Orange3MNE/EegClassification/widgets/RejectAmplitude.py
Orange3MNE/EegClassification/widgets/TrainTestSelect.py
Orange3MNE/EegClassification/widgets/TrainTestSplit.py
Orange3MNE/EegClassification/widgets/WindowedMeans.py
Orange3MNE/EegClassification/widgets/__init__.py
Orange3MNE/EegClassification/widgets/icons/averaging.png
Orange3MNE/EegClassification/widgets/icons/cnn-reshape.png
Orange3MNE/EegClassification/widgets/icons/cnn.png
Orange3MNE/EegClassification/widgets/icons/con-classification-structs.png
Orange3MNE/EegClassification/widgets/icons/create-classification-struct.png
Orange3MNE/EegClassification/widgets/icons/lda.png
Orange3MNE/EegClassification/widgets/icons/prepare-vectors.png
Orange3MNE/EegClassification/widgets/icons/rejection.png
Orange3MNE/EegClassification/widgets/icons/test-train-select.png
Orange3MNE/EegClassification/widgets/icons/test-train.png
Orange3MNE/EegClassification/widgets/icons/testing.png
Orange3MNE/EegClassification/widgets/icons/windowed-means.png
Orange3MNE/EegDataIO/__init__.py
Orange3MNE/EegDataIO/widgets/AbstractReader.py
Orange3_MNE-1.0.13.dist-info/LICENSE
Orange3_MNE-1.0.13.dist-info/METADATA
Orange3_MNE-1.0.13.dist-info/WHEEL
Orange3_MNE-1.0.13.dist-info/entry_points.txt
Orange3_MNE-1.0.13.dist-info/top_level.txt
Orange3_MNE-1.0.13.dist-info/RECORD
