Metadata-Version: 2.1
Name: Orange3-MNE
Version: 1.0.13
Summary: Electrophysiological data processing widgets for Orange 3 based on the MNE for Python library.
Home-page: https://gitlab.com/fifal/orange-mne-library
Author: Filip Jani
Author-email: jsem@filek.cz
License: UNKNOWN
Keywords: orange3 add-on,mne,eeg,electrophysiology
Platform: UNKNOWN
Classifier: Programming Language :: Python :: 3
Classifier: License :: OSI Approved :: GNU General Public License v3 (GPLv3)
Classifier: Operating System :: OS Independent
Requires-Python: >=3.7
License-File: LICENSE
Requires-Dist: mne (==1.1.1)
Requires-Dist: PyQt5
Requires-Dist: keras (==2.10.0)
Requires-Dist: keras-metrics (==1.1.0)
Requires-Dist: tensorflow (==2.10.0)
